{
  "teams": {
    "team1": {
      "games": {
        "1": { "opponent": "team3", "details": "Quiz Challenge vs Team 3" },
        "2": { "opponent": "team5", "details": "Memory Game vs Team 5" },
        "3": { "opponent": "team2", "details": "Strategy Battle vs Team 2" },
        "4": { "opponent": "team7", "details": "Speed Challenge vs Team 7" },
        "5": { "opponent": "team4", "details": "Logic Puzzle vs Team 4" },
        "6": { "opponent": "team6", "details": "Creative Task vs Team 6" },
        "7": { "opponent": "team8", "details": "Physical Challenge vs Team 8" },
        "8": { "opponent": "team9", "details": "Trivia Round vs Team 9" },
        "9": { "opponent": "team10", "details": "Problem Solving vs Team 10" },
        "10": { "opponent": "team11", "details": "Team Building vs Team 11" },
        "11": { "opponent": "team12", "details": "Final Challenge vs Team 12" },
        "12": { "opponent": "all", "details": "Grand Championship - All Teams" }
      }
    },
    "team2": {
      "games": {
        "1": { "opponent": "team4", "details": "Quiz Challenge vs Team 4" },
        "2": { "opponent": "team6", "details": "Memory Game vs Team 6" },
        "3": { "opponent": "team1", "details": "Strategy Battle vs Team 1" },
        "4": { "opponent": "team8", "details": "Speed Challenge vs Team 8" },
        "5": { "opponent": "team5", "details": "Logic Puzzle vs Team 5" },
        "6": { "opponent": "team7", "details": "Creative Task vs Team 7" },
        "7": { "opponent": "team9", "details": "Physical Challenge vs Team 9" },
        "8": { "opponent": "team10", "details": "Trivia Round vs Team 10" },
        "9": { "opponent": "team11", "details": "Problem Solving vs Team 11" },
        "10": { "opponent": "team12", "details": "Team Building vs Team 12" },
        "11": { "opponent": "team3", "details": "Final Challenge vs Team 3" },
        "12": { "opponent": "all", "details": "Grand Championship - All Teams" }
      }
    },
    "team3": {
      "games": {
        "1": { "opponent": "team1", "details": "Quiz Challenge vs Team 1" },
        "2": { "opponent": "team7", "details": "Memory Game vs Team 7" },
        "3": { "opponent": "team5", "details": "Strategy Battle vs Team 5" },
        "4": { "opponent": "team9", "details": "Speed Challenge vs Team 9" },
        "5": { "opponent": "team6", "details": "Logic Puzzle vs Team 6" },
        "6": { "opponent": "team8", "details": "Creative Task vs Team 8" },
        "7": { "opponent": "team10", "details": "Physical Challenge vs Team 10" },
        "8": { "opponent": "team11", "details": "Trivia Round vs Team 11" },
        "9": { "opponent": "team12", "details": "Problem Solving vs Team 12" },
        "10": { "opponent": "team4", "details": "Team Building vs Team 4" },
        "11": { "opponent": "team2", "details": "Final Challenge vs Team 2" },
        "12": { "opponent": "all", "details": "Grand Championship - All Teams" }
      }
    },
    "team4": {
      "games": {
        "1": { "opponent": "team2", "details": "Quiz Challenge vs Team 2" },
        "2": { "opponent": "team8", "details": "Memory Game vs Team 8" },
        "3": { "opponent": "team6", "details": "Strategy Battle vs Team 6" },
        "4": { "opponent": "team10", "details": "Speed Challenge vs Team 10" },
        "5": { "opponent": "team1", "details": "Logic Puzzle vs Team 1" },
        "6": { "opponent": "team9", "details": "Creative Task vs Team 9" },
        "7": { "opponent": "team11", "details": "Physical Challenge vs Team 11" },
        "8": { "opponent": "team12", "details": "Trivia Round vs Team 12" },
        "9": { "opponent": "team3", "details": "Problem Solving vs Team 3" },
        "10": { "opponent": "team3", "details": "Team Building vs Team 3" },
        "11": { "opponent": "team5", "details": "Final Challenge vs Team 5" },
        "12": { "opponent": "all", "details": "Grand Championship - All Teams" }
      }
    },
    "team5": {
      "games": {
        "1": { "opponent": "team6", "details": "Quiz Challenge vs Team 6" },
        "2": { "opponent": "team1", "details": "Memory Game vs Team 1" },
        "3": { "opponent": "team3", "details": "Strategy Battle vs Team 3" },
        "4": { "opponent": "team11", "details": "Speed Challenge vs Team 11" },
        "5": { "opponent": "team2", "details": "Logic Puzzle vs Team 2" },
        "6": { "opponent": "team10", "details": "Creative Task vs Team 10" },
        "7": { "opponent": "team12", "details": "Physical Challenge vs Team 12" },
        "8": { "opponent": "team7", "details": "Trivia Round vs Team 7" },
        "9": { "opponent": "team8", "details": "Problem Solving vs Team 8" },
        "10": { "opponent": "team9", "details": "Team Building vs Team 9" },
        "11": { "opponent": "team4", "details": "Final Challenge vs Team 4" },
        "12": { "opponent": "all", "details": "Grand Championship - All Teams" }
      }
    },
    "team6": {
      "games": {
        "1": { "opponent": "team5", "details": "Quiz Challenge vs Team 5" },
        "2": { "opponent": "team2", "details": "Memory Game vs Team 2" },
        "3": { "opponent": "team4", "details": "Strategy Battle vs Team 4" },
        "4": { "opponent": "team12", "details": "Speed Challenge vs Team 12" },
        "5": { "opponent": "team3", "details": "Logic Puzzle vs Team 3" },
        "6": { "opponent": "team1", "details": "Creative Task vs Team 1" },
        "7": { "opponent": "team7", "details": "Physical Challenge vs Team 7" },
        "8": { "opponent": "team8", "details": "Trivia Round vs Team 8" },
        "9": { "opponent": "team9", "details": "Problem Solving vs Team 9" },
        "10": { "opponent": "team10", "details": "Team Building vs Team 10" },
        "11": { "opponent": "team11", "details": "Final Challenge vs Team 11" },
        "12": { "opponent": "all", "details": "Grand Championship - All Teams" }
      }
    },
    "team7": {
      "games": {
        "1": { "opponent": "team8", "details": "Quiz Challenge vs Team 8" },
        "2": { "opponent": "team3", "details": "Memory Game vs Team 3" },
        "3": { "opponent": "team9", "details": "Strategy Battle vs Team 9" },
        "4": { "opponent": "team1", "details": "Speed Challenge vs Team 1" },
        "5": { "opponent": "team10", "details": "Logic Puzzle vs Team 10" },
        "6": { "opponent": "team2", "details": "Creative Task vs Team 2" },
        "7": { "opponent": "team6", "details": "Physical Challenge vs Team 6" },
        "8": { "opponent": "team5", "details": "Trivia Round vs Team 5" },
        "9": { "opponent": "team11", "details": "Problem Solving vs Team 11" },
        "10": { "opponent": "team12", "details": "Team Building vs Team 12" },
        "11": { "opponent": "team4", "details": "Final Challenge vs Team 4" },
        "12": { "opponent": "all", "details": "Grand Championship - All Teams" }
      }
    },
    "team8": {
      "games": {
        "1": { "opponent": "team7", "details": "Quiz Challenge vs Team 7" },
        "2": { "opponent": "team4", "details": "Memory Game vs Team 4" },
        "3": { "opponent": "team10", "details": "Strategy Battle vs Team 10" },
        "4": { "opponent": "team2", "details": "Speed Challenge vs Team 2" },
        "5": { "opponent": "team11", "details": "Logic Puzzle vs Team 11" },
        "6": { "opponent": "team3", "details": "Creative Task vs Team 3" },
        "7": { "opponent": "team1", "details": "Physical Challenge vs Team 1" },
        "8": { "opponent": "team6", "details": "Trivia Round vs Team 6" },
        "9": { "opponent": "team5", "details": "Problem Solving vs Team 5" },
        "10": { "opponent": "team9", "details": "Team Building vs Team 9" },
        "11": { "opponent": "team12", "details": "Final Challenge vs Team 12" },
        "12": { "opponent": "all", "details": "Grand Championship - All Teams" }
      }
    }
  }
}
